romcal/__init__.py
romcal/_uniffi/__init__.py
romcal/_uniffi/libromcal_uniffi.dylib
romcal/_uniffi/romcal_uniffi.py
romcal/py.typed
romcal/types.py
romcal-4.0.0b5.dist-info/METADATA
romcal-4.0.0b5.dist-info/WHEEL
romcal-4.0.0b5.dist-info/RECORD
