Metadata-Version: 2.4
Name: romcal
Version: 4.0.0b5
Classifier: Development Status :: 4 - Beta
Classifier: Intended Audience :: Developers
Classifier: License :: OSI Approved :: Apache Software License
Classifier: Programming Language :: Python :: 3
Classifier: Programming Language :: Python :: 3.11
Classifier: Programming Language :: Python :: 3.12
Classifier: Programming Language :: Python :: 3.13
Classifier: Programming Language :: Python :: 3.14
Classifier: Programming Language :: Rust
Classifier: Topic :: Religion
Classifier: Topic :: Software Development :: Libraries :: Python Modules
Requires-Dist: pydantic>=2.0
Requires-Dist: pytest>=8.0 ; extra == 'dev'
Requires-Dist: taskipy>=1.13 ; extra == 'dev'
Requires-Dist: ruff>=0.8 ; extra == 'dev'
Requires-Dist: mypy>=1.13 ; extra == 'dev'
Provides-Extra: dev
Summary: Liturgical calendar library for calculating Catholic liturgical dates and calendars
Keywords: liturgical,calendar,catholic,roman-rite,church
Author-email: Étienne Magnier <etienne.magnier@gmail.com>
License: Apache-2.0
Requires-Python: >=3.11
Project-URL: Documentation, https://github.com/emagnier/romcal#readme
Project-URL: Homepage, https://github.com/emagnier/romcal
Project-URL: Repository, https://github.com/emagnier/romcal
